<?xml version="1.0" encoding="utf-8" ?><dwsync><file name="call-to-action-1.jpg" server="churchillmedia.wpengine.com:2222" local="3554735536" remote="3581316430" Dst="-1" /><file name="call-to-action-1@2x.jpg" server="churchillmedia.wpengine.com:2222" local="3554735536" remote="3581316431" Dst="-1" /><file name="hero-1.jpg" server="churchillmedia.wpengine.com:2222" local="3554735536" remote="3581316431" Dst="-1" /><file name="hero-1@2x.jpg" server="churchillmedia.wpengine.com:2222" local="3554735536" remote="3581316431" Dst="-1" /><file name="hero-half-1.jpg" server="churchillmedia.wpengine.com:2222" local="3554735536" remote="3581316432" Dst="-1" /><file name="hero-half-1@2x.jpg" server="churchillmedia.wpengine.com:2222" local="3554735536" remote="3581316432" Dst="-1" /><file name="hero-half-2.jpg" server="churchillmedia.wpengine.com:2222" local="3554735536" remote="3581316432" Dst="-1" /><file name="hero-half-2@2x.jpg" server="churchillmedia.wpengine.com:2222" local="3554735538" remote="3581316433" Dst="-1" /><file name="hero-half-3.jpg" server="churchillmedia.wpengine.com:2222" local="3554735538" remote="3581316433" Dst="-1" /><file name="hero-half-3@2x.jpg" server="churchillmedia.wpengine.com:2222" local="3554735538" remote="3581316433" Dst="-1" /><file name="signup-1.jpg" server="churchillmedia.wpengine.com:2222" local="3554735538" remote="3581316434" Dst="-1" /><file name="signup-1@2x.jpg" server="churchillmedia.wpengine.com:2222" local="3554735538" remote="3581316434" Dst="-1" /><file name="team-member-1-portrait.jpg" server="churchillmedia.wpengine.com:2222" local="3554735540" remote="3581316435" Dst="-1" /><file name="team-member-2.jpg" server="churchillmedia.wpengine.com:2222" local="3554735540" remote="3581316435" Dst="-1" /></dwsync>